cli_parser/.git/HEAD
cli_parser/.git/config
cli_parser/.git/description
cli_parser/.git/hooks/applypatch-msg.sample
cli_parser/.git/hooks/commit-msg.sample
cli_parser/.git/hooks/fsmonitor-watchman.sample
cli_parser/.git/hooks/post-update.sample
cli_parser/.git/hooks/pre-applypatch.sample
cli_parser/.git/hooks/pre-commit.sample
cli_parser/.git/hooks/pre-push.sample
cli_parser/.git/hooks/pre-rebase.sample
cli_parser/.git/hooks/pre-receive.sample
cli_parser/.git/hooks/prepare-commit-msg.sample
cli_parser/.git/hooks/update.sample
cli_parser/.git/info/exclude
cli_parser/__init__.py
cli_parser/commands.py
cli_parser/exceptions.py
cli_parser/parser.py
cli_parser/utils.py
cli_parser-0.1.3.dist-info/WHEEL
cli_parser-0.1.3.dist-info/METADATA
cli_parser-0.1.3.dist-info/RECORD
