Metadata-Version: 2.1
Name: cli-parser
Version: 0.1.3
Summary: Simple CLI Parser with command chaining
Home-page: https://github.com/ranzvi/cli_parser
License: MIT
Keywords: CLI,Python,Tool,Simple
Author: Ran Zvi
Author-email: ran.zvi@bluevine.com
Maintainer: Ran Zvi
Maintainer-email: ran.zvi@bluevine.com
Requires-Python: >=3.6,<4.0
Classifier: License :: OSI Approved :: MIT License
Classifier: Programming Language :: Python :: 3
Classifier: Programming Language :: Python :: 3.6
Classifier: Programming Language :: Python :: 3.7
Classifier: Programming Language :: Python :: 3.8
Project-URL: Repository, https://github.com/ranzvi/cli_parser
